serialcables_atlas3/__init__.py
serialcables_atlas3/atlas3.py
serialcables_atlas3/cli.py
serialcables_atlas3/exceptions.py
serialcables_atlas3/models.py
serialcables_atlas3/parsers.py
serialcables_atlas3/py.typed
serialcables_atlas3-0.1.5.dist-info/licenses/LICENSE
serialcables_atlas3-0.1.5.dist-info/METADATA
serialcables_atlas3-0.1.5.dist-info/WHEEL
serialcables_atlas3-0.1.5.dist-info/entry_points.txt
serialcables_atlas3-0.1.5.dist-info/top_level.txt
serialcables_atlas3-0.1.5.dist-info/RECORD
