Metadata-Version: 2.4
Name: serialcables-atlas3
Version: 0.1.5
Summary: Python API for Serial Cables Atlas3 PCIe Gen6 Host Adapter Card
Author-email: Serial Cables <support@serialcables.com>
Maintainer-email: Serial Cables <support@serialcables.com>
License: MIT
Project-URL: Homepage, https://serialcables.com
Project-URL: Documentation, https://github.com/serialcables/serialcables-atlas3#readme
Project-URL: Repository, https://github.com/serialcables/serialcables-atlas3
Project-URL: Issues, https://github.com/serialcables/serialcables-atlas3/issues
Keywords: pcie,gen6,atlas3,broadcom,pex90144,nvme,ssd,serial-cables,hardware,mcio
Classifier: Development Status :: 4 - Beta
Classifier: Intended Audience :: Developers
Classifier: Intended Audience :: System Administrators
Classifier: License :: OSI Approved :: MIT License
Classifier: Operating System :: OS Independent
Classifier: Programming Language :: Python :: 3
Classifier: Programming Language :: Python :: 3.8
Classifier: Programming Language :: Python :: 3.9
Classifier: Programming Language :: Python :: 3.10
Classifier: Programming Language :: Python :: 3.11
Classifier: Programming Language :: Python :: 3.12
Classifier: Topic :: System :: Hardware
Classifier: Topic :: System :: Hardware :: Hardware Drivers
Classifier: Topic :: Software Development :: Libraries :: Python Modules
Requires-Python: >=3.8
License-File: LICENSE
Requires-Dist: pyserial>=3.5
Provides-Extra: dev
Requires-Dist: pytest>=7.0; extra == "dev"
Requires-Dist: pytest-cov>=4.0; extra == "dev"
Requires-Dist: black>=23.0; python_version >= "3.9" and extra == "dev"
Requires-Dist: black<25.0,>=22.0; python_version == "3.8" and extra == "dev"
Requires-Dist: isort<6.0,>=5.12; extra == "dev"
Requires-Dist: mypy>=1.0; python_version >= "3.9" and extra == "dev"
Requires-Dist: ruff>=0.1.0; extra == "dev"
Requires-Dist: types-pyserial>=3.5; extra == "dev"
Provides-Extra: docs
Requires-Dist: sphinx>=6.0; extra == "docs"
Requires-Dist: sphinx-rtd-theme>=1.0; extra == "docs"
Dynamic: license-file
